uniquipy/analyze.py
uniquipy/cli.py
uniquipy/pack.py
uniquipy/src.py
uniquipy-1.1.0.dist-info/LICENSE
uniquipy-1.1.0.dist-info/METADATA
uniquipy-1.1.0.dist-info/WHEEL
uniquipy-1.1.0.dist-info/entry_points.txt
uniquipy-1.1.0.dist-info/top_level.txt
uniquipy-1.1.0.dist-info/RECORD
