Metadata-Version: 2.1
Name: uniquipy
Version: 1.1.0
Summary: python cli-tool to find and handle file duplicates
Home-page: https://pypi.org/project/uniquipy/
Author: Steffen Richters-Finger
Author-email: srichters@uni-muenster.de
License: MIT
Project-URL: Source, https://github.com/RichtersFinger/uniquipy
Platform: UNKNOWN
Requires-Python: >=3.9, <4
License-File: LICENSE
Requires-Dist: click <9.0.0,>=8.1.7
